Metadata-Version: 1.0
Name: chromatic
Version: 1.0.3
Summary: Generate monochromatic backgrounds instantly
Home-page: https://github.com/prakashdanish/chromatic
Author: Danish Prakash
Author-email: danishprakash@outlook.com
License: UNKNOWN
Platform: UNKNOWN
